wt/__init__.py
wt/py.typed
wt/cli/__init__.py
wt/cli/main.py
wt/config/README.md
wt/config/__init__.py
wt/config/loader.py
wt/config/settings.py
wt/core/__init__.py
wt/core/exceptions.py
wt/core/models.py
wt/core/repository.py
wt/tui/__init__.py
wt/tui/app.py
wt/tui/app.tcss
python_wt-0.1.0.dist-info/METADATA
python_wt-0.1.0.dist-info/WHEEL
python_wt-0.1.0.dist-info/entry_points.txt
python_wt-0.1.0.dist-info/licenses/LICENSE
python_wt-0.1.0.dist-info/RECORD
