Metadata-Version: 2.4
Name: python-wt
Version: 0.1.0
Summary: The ultimate git worktree manager with beautiful TUI and modern CLI
Project-URL: Homepage, https://github.com/ajcasagrande/pywt
Project-URL: Documentation, https://pywt.readthedocs.io
Project-URL: Repository, https://github.com/ajcasagrande/pywt
Project-URL: Issues, https://github.com/ajcasagrande/pywt/issues
Author: Anthony Casagrande
License: MIT
License-File: LICENSE
Keywords: cli,developer-tools,git,tui,worktree
Classifier: Development Status :: 5 - Production/Stable
Classifier: Environment :: Console
Classifier: Intended Audience :: Developers
Classifier: License :: OSI Approved :: MIT License
Classifier: Operating System :: OS Independent
Classifier: Programming Language :: Python :: 3
Classifier: Programming Language :: Python :: 3.12
Classifier: Programming Language :: Python :: 3.13
Classifier: Topic :: Software Development :: Version Control :: Git
Classifier: Topic :: Utilities
Classifier: Typing :: Typed
Requires-Python: >=3.12
Requires-Dist: cyclopts>=2.9.0
Requires-Dist: platformdirs>=4.3.0
Requires-Dist: pydantic>=2.9.0
Requires-Dist: rich>=13.9.0
Requires-Dist: textual>=0.82.0
Requires-Dist: tomli>=2.0.0; python_version < '3.11'
Provides-Extra: dev
Requires-Dist: mypy>=1.13.0; extra == 'dev'
Requires-Dist: pytest-asyncio>=0.24.0; extra == 'dev'
Requires-Dist: pytest-cov>=5.0.0; extra == 'dev'
Requires-Dist: pytest-mock>=3.14.0; extra == 'dev'
Requires-Dist: pytest>=8.3.0; extra == 'dev'
Requires-Dist: ruff>=0.7.0; extra == 'dev'
Requires-Dist: types-psutil; extra == 'dev'
